{
  "Vianense":[
      {
          "id":1,
          "nome": "Açúcar refinado Caravelas 1kg", 
          "imagem": "../src/assets/caravelas.jpg", 
          "preco": "R$ 1,89"
      },
      {
          "id":2,
          "nome": "Arroz Picó 5kg", 
          "imagem": "../src/assets/pico.jpg", 
          "preco": " R$ 10,95"
      },
      {
          "id":3,
          "nome": "Leite condençado Moça 395g", 
          "imagem": "../src/assets/moca.jpg", 
          "preco": "R$ 3,99"
      },
      {
          "id":4,
          "nome": "Filé de peito de frango com pele kg", 
          "imagem":"../src/assets/file-peito.jpg" , 
          "preco": "R$ 9,98"
      },
      {
          "id":5,
          "nome": "café Pimpinela Golden 500g", 
          "imagem":"../src/assets/pimpinela.jpg" , 
          "preco": "R$ 8,78"
      }
  ]
}